nerdpool_client/__init__.py
nerdpool_client-1.1.0.dist-info/METADATA
nerdpool_client-1.1.0.dist-info/WHEEL
nerdpool_client-1.1.0.dist-info/top_level.txt
nerdpool_client-1.1.0.dist-info/RECORD
